LICENSE.txt
README.md
__init__.py
conf.py
setup.py
./__init__.py
./conf.py
pnh.egg-info/PKG-INFO
pnh.egg-info/SOURCES.txt
pnh.egg-info/dependency_links.txt
pnh.egg-info/top_level.txt
utils/__init__.py
utils/calc_k_from_dp.py
utils/gen_model_from_nx.py