Metadata-Version: 2.1
Name: pnh
Version: 0.0.8
Summary: pnh
License-File: LICENSE.txt
